<?xml version="1.0" encoding="utf-8"?><?xml-stylesheet type='text/xsl' href="http://cdastyle.e-mds.com/cda3.xsl"?><ClinicalDocument xmlns:xsi="http://www.w3.org/2001/XMLSchema-instance" xmlns:xsd="http://www.w3.org/2001/XMLSchema" xmlns:mif="urn:hl7-org:v3/mif" xmlns:sdtc="urn:hl7-org:sdtc" xsi:schemaLocation="urn:hl7-org:v3 http://emds-iportal/development/Interfaces/CDA/CDASchemas/cda/Schemas/CDA.xsd" xmlns="urn:hl7-org:v3"><realmCode code="US" /><typeId root="2.16.840.1.113883.1.3" extension="POCD_HD000040" /><templateId root="2.16.840.1.113883.3.27.1776" assigningAuthorityName="CDA/R2" /><templateId root="2.16.840.1.113883.10.20.1" assigningAuthorityName="CCD" /><templateId root="1.3.6.1.4.1.19376.1.5.3.1.1.1" /><templateId root="2.16.840.1.113883.10.20.3" /><templateId root="2.16.840.1.113883.3.88.11.32.1" /><id root="e07ddd6e-12aa-4708-bcc1-37b7f69c3c39" /><code code="34133-9" codeSystem="2.16.840.1.113883.6.1" codeSystemName="LOINC" displayName="Summary of episode note" /><title>Visit Summary for 6/6/2012</title><effectiveTime value="20120606172803-0400" /><confidentialityCode code="N" codeSystem="2.16.840.1.113883.5.25" /><languageCode code="en-US" /><recordTarget><patientRole><id root="2.16.840.1.113883.4.317" extension="TESTES0001" assigningAuthorityName="e-MDs" /><addr use="HP"><streetAddressLine>123 Main Street</streetAddressLine><city>Smyrna</city><state>GA</state><postalCode>30080</postalCode><country>US</country></addr><telecom use="HP" value="tel:(678)705-7341" /><telecom use="MC" value="tel:(678)705-7341" /><patient><name><given>Child Female</given><family>Test</family></name><administrativeGenderCode code="F" codeSystem="2.16.840.1.113883.5.1" /><birthTime value="20000101" /><maritalStatusCode code="D" codeSystem="2.16.840.1.113883.5.2" codeSystemName="MaritalStatus" displayName="Divorced" /><languageCommunication><templateId root="2.16.840.1.113883.3.88.11.83.2" /><templateId root="1.3.6.1.4.1.19376.1.5.3.1.2.1" /><languageCode code="en-US" /><preferenceInd value="true" /></languageCommunication></patient><providerOrganization><id root="2.16.840.1.113883.4.6" extension="1689740987" /><name /><telecom /><addr nullFlavor="UNK" /></providerOrganization></patientRole></recordTarget><author><time value="20120606172803" /><assignedAuthor><id root="7d337e97-197d-4b5e-8c12-c633f6b3735d" /><addr /><telecom value="mailto:fberenson@atlantaheadachespecialists.com" /><assignedPerson><name><prefix>Dr.</prefix><given>Frank</given><family>Berenson</family></name></assignedPerson><representedOrganization><name>Atlanta Headache Specialists &amp; PANDA Neurology</name><telecom use="WP" value="tel:(678)705-7341" /><telecom use="WP" value="fax:(678)973-0578" /><addr use="WP"><streetAddressLine>5887 Glenridge Drive Suite 140</streetAddressLine><city>Atlanta</city><state>GA</state><postalCode>30328-5577</postalCode><country>US</country></addr></representedOrganization></assignedAuthor></author><author><time value="20120606172803" /><assignedAuthor><id root="e1113176-70d2-45af-aac0-d1b96a2cee47" /><addr /><telecom /><assignedAuthoringDevice><softwareName>e-MDs;SDB:1.1.4476.17630;</softwareName></assignedAuthoringDevice></assignedAuthor></author><custodian><assignedCustodian><representedCustodianOrganization><id root="2.16.840.1.113883.4.317" extension="AHS&amp;PN" assigningAuthorityName="e-MDs" /><name>Atlanta Headache Specialists &amp; PANDA Neurology</name><telecom use="WP" value="tel:(678)705-7341" /><addr use="WP"><streetAddressLine>5887 Glenridge Drive Suite 140</streetAddressLine><city>Atlanta</city><state>GA</state><postalCode>30328-5577</postalCode><country>US</country></addr></representedCustodianOrganization></assignedCustodian></custodian><legalAuthenticator><time value="20120606172803" /><signatureCode /><assignedEntity><id root="ac96be23-8cfe-4eef-a6f6-0f87ba5d7661" /><addr use="WP"><streetAddressLine>5887 Glenridge Drive Suite 140</streetAddressLine><city>Atlanta</city><state>GA</state><postalCode>30328-5577</postalCode><country>US</country></addr><telecom use="WP" value="tel:(678)705-7341" /><telecom use="WP" value="fax:(678)973-0578" /><assignedPerson><name><prefix>Dr.</prefix><given>Frank</given><family>Berenson</family></name></assignedPerson><representedOrganization><name>Atlanta Headache Specialists &amp; PANDA Neurology</name><telecom use="WP" value="tel:(678)705-7341" /><telecom use="WP" value="fax:(678)973-0578" /><addr use="WP"><streetAddressLine>5887 Glenridge Drive Suite 140</streetAddressLine><city>Atlanta</city><state>GA</state><postalCode>30328-5577</postalCode><country>US</country></addr></representedOrganization></assignedEntity></legalAuthenticator><documentationOf><serviceEvent classCode="PCPR"><effectiveTime><low value="20120606093641" /><high value="20120606172803" /></effectiveTime><performer typeCode="PRF"><assignedEntity><id root="c5802955-e97b-476e-912f-912acd132790" /><addr use="WP"><streetAddressLine>5887 Glenridge Drive Suite 140</streetAddressLine><city>Atlanta</city><state>GA</state><postalCode>30328-5577</postalCode><country>US</country></addr><telecom use="WP" value="tel:(678)705-7341" /><telecom use="WP" value="fax:(678)973-0578" /><assignedPerson><name><prefix>Dr.</prefix><given>Frank</given><family>Berenson</family></name></assignedPerson><representedOrganization><name>Atlanta Headache Specialists &amp; PANDA Neurology</name><telecom use="WP" value="tel:(678)705-7341" /><telecom use="WP" value="fax:(678)973-0578" /><addr use="WP"><streetAddressLine>5887 Glenridge Drive Suite 140</streetAddressLine><city>Atlanta</city><state>GA</state><postalCode>30328-5577</postalCode><country>US</country></addr></representedOrganization></assignedEntity></performer></serviceEvent></documentationOf><component><structuredBody><component><section><templateId root="1.3.6.1.4.1.19376.1.5.3.1.1.13.2.1" /><id root="6add30ef-b3ab-4437-b3f1-c7e8f0e2527d" /><code code="10154-3" codeSystem="2.16.840.1.113883.6.1" codeSystemName="CHIEF COMPLAINT" displayName="LOINC" /><title>Reason for Visit</title><text><paragraph>Testing 1 2 3 is a 12 year old female. This is a follow-up visit. She presents with seizures .</paragraph><paragraph>Visit date occurred: 6/6/2012</paragraph></text></section></component><component><section><templateId root="1.3.6.1.4.1.19376.1.5.3.1.3.4" /><id root="c668e754-4c86-454f-9546-f67607655413" /><code code="10164-2" codeSystem="2.16.840.1.113883.6.1" codeSystemName="LOINC" displayName="HISTORY OF PRESENT ILLNESS" /><title>History of Present Illness</title><text><list><item>Joe shmoe had a big doozy of a seizure. </item><item>Testing 1 2 3 presents with seizure(s).  Testing 1 2 3 has been diagnosed with simple partial seizures.  There was no known precipitating event for the seizures.  Witnessed seizure activity is described as generalized convulsion.  The duration of the last (most recent) seizure was approximately 5 minutes.  During the course of treatment there have been no new seizures.  Current seizure medications include Ethotoin and Methsuximide.  </item></list></text></section></component><component><section><templateId root="2.16.840.1.113883.10.20.1.16" /><id root="44fa169a-a16e-4146-9fd1-6c6dba14c446" /><code code="8716-3" codeSystem="2.16.840.1.113883.6.1" codeSystemName="LOINC" displayName="Vital Signs" /><title>Vitals</title><text><paragraph>No vitals listed.</paragraph></text></section></component><component><section><templateId root="2.16.840.1.113883.10.20.1.14" /><templateId root="1.3.6.1.4.1.19376.1.5.3.1.3.28" /><templateId root="2.16.840.1.113883.3.88.11.83.122" /><id root="da1cf00f-fc8e-4eae-9a1d-b21391911fad" /><code code="30954-2" codeSystem="2.16.840.1.113883.6.1" codeSystemName="LOINC" displayName="Relevant diagnostic tests/laboratory data" /><title>Diagnostic Test Results</title><text /><entry typeCode="DRIV"><procedure classCode="PROC" moodCode="EVN"><templateId root="1.3.6.1.4.1.19376.1.5.3.1.4.19" /><templateId root="2.16.840.1.113883.3.88.11.83.17" /><templateId root="2.16.840.1.113883.10.20.1.29" /><id root="7990deee-d385-4d8e-b474-30b32da2893a" /><code><originalText><reference value="#labcode-dummy" /></originalText></code><text><reference value="#labtest-dummy" /></text><statusCode code="completed" /><entryRelationship typeCode="REFR"><observation classCode="OBS" moodCode="EVN"><templateId root="2.16.840.1.113883.3.88.11.32.16" /><templateId root="2.16.840.1.113883.3.88.11.83.15.1" /><templateId root="2.16.840.1.113883.10.20.1.31" /><templateId root="1.3.6.1.4.1.19376.1.5.3.1.4.13" /><id root="ce81e8ba-10b8-4252-8e78-e1779d14a6d8" /><code code="UNK" codeSystemName="eMDs" /><text><reference value="#labresult-dummy" /></text><statusCode code="completed" /><effectiveTime value="20010101000000" /><value xsi:type="CD" displayName="0" /></observation></entryRelationship></procedure></entry></section></component><component><section><templateId root="2.16.840.1.113883.10.20.1.11" /><templateId root="2.16.840.1.113883.3.88.11.83.103" /><templateId root="1.3.6.1.4.1.19376.1.5.3.1.3.6" /><id root="74a91f99-1958-46c7-8a3e-4fe02d75e7f1" /><code code="11450-4" codeSystem="2.16.840.1.113883.6.1" codeSystemName="LOINC" displayName="PROBLEM LIST" /><title>Problem List</title><text><list><item><content ID="problem-ZZZZZ0070Z">Complex Partial seizure w/o intract</content> - 345.40, diagnosed 6/6/2012</item><item><content ID="problem-ZZZZZ003AE">Mixed seizures</content> - 345.90, diagnosed 4/4/2012</item><item><content ID="problem-ZZZZZ003HG">Seizures</content> - 780.39, diagnosed 3/1/2012</item><item><content ID="problem-ZZZZZ001OI">Petit mal seizure disorder</content> - 345.00, diagnosed 3/1/2012</item><item><content ID="problem-ZZZZZ0031L">Classic migraine</content> - 346.00, diagnosed 3/1/2012</item><item><content ID="problem-ZZZZZ003HI">ADHD</content> - 314.01, diagnosed 3/1/2012</item><item><content ID="problem-ZZZZZ000S2">Common migraine</content> - 346.10, diagnosed 2/14/2012</item><item><content ID="problem-ZZZZZ001OP">Migraine with aura</content> - 346.00, diagnosed 2/10/2012</item><item><content ID="problem-ZZZZZ000DQ">Heat intolerance</content> - 780.99, diagnosed 2/8/2012</item></list></text><entry><act classCode="ACT" moodCode="EVN"><templateId root="2.16.840.1.113883.3.88.11.83.7" /><templateId root="2.16.840.1.113883.10.20.1.27" /><templateId root="1.3.6.1.4.1.19376.1.5.3.1.4.5.1" /><templateId root="1.3.6.1.4.1.19376.1.5.3.1.4.5.2" /><id root="7a1dddff-0a5e-478b-9aad-6fd9b58a201c" /><code nullFlavor="NA" /><statusCode code="active" /><effectiveTime><low value="20120606000000" /></effectiveTime><entryRelationship typeCode="SUBJ" inversionInd="false"><observation classCode="OBS" moodCode="EVN"><templateId root="2.16.840.1.113883.10.20.1.28" /><templateId root="1.3.6.1.4.1.19376.1.5.3.1.4.5" /><templateId root="2.16.840.1.113883.3.249.11.100.8" /><id root="919e9922-38ef-4e70-902a-15e5a12dbd00" /><code code="55607006" codeSystem="2.16.840.1.113883.6.96" codeSystemName="SNOMED CT" displayName="Problem" /><text><reference value="#problem-ZZZZZ0070Z" /></text><statusCode code="completed" /><effectiveTime><low value="20120606000000" /></effectiveTime><value xsi:type="CD" nullFlavor="UNK"><translation code="345.40" codeSystem="2.16.840.1.113883.6.103" codeSystemName="ICD-9" /></value><entryRelationship typeCode="REFR"><observation classCode="OBS" moodCode="EVN"><templateId root="2.16.840.1.113883.10.20.1.50" /><templateId root="2.16.840.1.113883.3.249.11.100.12" /><id root="cfcaa07f-00ba-44f8-ac8a-4120a9cff00a" /><code code="33999-4" codeSystem="2.16.840.1.113883.6.1" displayName="Status" /><statusCode code="active" /><value xsi:type="CE" code="55561003" codeSystem="2.16.840.1.113883.6.96" /></observation></entryRelationship></observation></entryRelationship></act></entry><entry><act classCode="ACT" moodCode="EVN"><templateId root="2.16.840.1.113883.3.88.11.83.7" /><templateId root="2.16.840.1.113883.10.20.1.27" /><templateId root="1.3.6.1.4.1.19376.1.5.3.1.4.5.1" /><templateId root="1.3.6.1.4.1.19376.1.5.3.1.4.5.2" /><id root="1985e29b-319b-463c-b53a-463871f18381" /><code nullFlavor="NA" /><statusCode code="active" /><effectiveTime><low value="20120404000000" /></effectiveTime><entryRelationship typeCode="SUBJ" inversionInd="false"><observation classCode="OBS" moodCode="EVN"><templateId root="2.16.840.1.113883.10.20.1.28" /><templateId root="1.3.6.1.4.1.19376.1.5.3.1.4.5" /><templateId root="2.16.840.1.113883.3.249.11.100.8" /><id root="030af9c9-2530-4449-8a1c-defb1e4e60c1" /><code code="55607006" codeSystem="2.16.840.1.113883.6.96" codeSystemName="SNOMED CT" displayName="Problem" /><text><reference value="#problem-ZZZZZ003AE" /></text><statusCode code="completed" /><effectiveTime><low value="20120404000000" /></effectiveTime><value xsi:type="CD" nullFlavor="UNK"><translation code="345.90" codeSystem="2.16.840.1.113883.6.103" codeSystemName="ICD-9" /></value><entryRelationship typeCode="REFR"><observation classCode="OBS" moodCode="EVN"><templateId root="2.16.840.1.113883.10.20.1.50" /><templateId root="2.16.840.1.113883.3.249.11.100.12" /><id root="31d7c41b-b321-4a33-96eb-e576e40feca1" /><code code="33999-4" codeSystem="2.16.840.1.113883.6.1" displayName="Status" /><statusCode code="active" /><value xsi:type="CE" code="55561003" codeSystem="2.16.840.1.113883.6.96" /></observation></entryRelationship></observation></entryRelationship></act></entry><entry><act classCode="ACT" moodCode="EVN"><templateId root="2.16.840.1.113883.3.88.11.83.7" /><templateId root="2.16.840.1.113883.10.20.1.27" /><templateId root="1.3.6.1.4.1.19376.1.5.3.1.4.5.1" /><templateId root="1.3.6.1.4.1.19376.1.5.3.1.4.5.2" /><id root="a1f1534a-18da-4e1a-982a-a503b63efec4" /><code nullFlavor="NA" /><statusCode code="active" /><effectiveTime><low value="20120301000000" /></effectiveTime><entryRelationship typeCode="SUBJ" inversionInd="false"><observation classCode="OBS" moodCode="EVN"><templateId root="2.16.840.1.113883.10.20.1.28" /><templateId root="1.3.6.1.4.1.19376.1.5.3.1.4.5" /><templateId root="2.16.840.1.113883.3.249.11.100.8" /><id root="1f50b7c1-43f7-4a19-86cc-828c41917d2f" /><code code="55607006" codeSystem="2.16.840.1.113883.6.96" codeSystemName="SNOMED CT" displayName="Problem" /><text><reference value="#problem-ZZZZZ003HG" /></text><statusCode code="completed" /><effectiveTime><low value="20120301000000" /></effectiveTime><value xsi:type="CD" nullFlavor="UNK"><translation code="780.39" codeSystem="2.16.840.1.113883.6.103" codeSystemName="ICD-9" /></value><entryRelationship typeCode="REFR"><observation classCode="OBS" moodCode="EVN"><templateId root="2.16.840.1.113883.10.20.1.50" /><templateId root="2.16.840.1.113883.3.249.11.100.12" /><id root="dc855540-7607-4a93-a804-c858e536fb68" /><code code="33999-4" codeSystem="2.16.840.1.113883.6.1" displayName="Status" /><statusCode code="active" /><value xsi:type="CE" code="55561003" codeSystem="2.16.840.1.113883.6.96" /></observation></entryRelationship></observation></entryRelationship></act></entry><entry><act classCode="ACT" moodCode="EVN"><templateId root="2.16.840.1.113883.3.88.11.83.7" /><templateId root="2.16.840.1.113883.10.20.1.27" /><templateId root="1.3.6.1.4.1.19376.1.5.3.1.4.5.1" /><templateId root="1.3.6.1.4.1.19376.1.5.3.1.4.5.2" /><id root="8fbd2287-35fe-48b6-849f-3504412dfad9" /><code nullFlavor="NA" /><statusCode code="active" /><effectiveTime><low value="20120301000000" /></effectiveTime><entryRelationship typeCode="SUBJ" inversionInd="false"><observation classCode="OBS" moodCode="EVN"><templateId root="2.16.840.1.113883.10.20.1.28" /><templateId root="1.3.6.1.4.1.19376.1.5.3.1.4.5" /><templateId root="2.16.840.1.113883.3.249.11.100.8" /><id root="cc0bac35-39b0-4fad-ae9e-3db6a3c561e0" /><code code="55607006" codeSystem="2.16.840.1.113883.6.96" codeSystemName="SNOMED CT" displayName="Problem" /><text><reference value="#problem-ZZZZZ001OI" /></text><statusCode code="completed" /><effectiveTime><low value="20120301000000" /></effectiveTime><value xsi:type="CD" nullFlavor="UNK"><translation code="345.00" codeSystem="2.16.840.1.113883.6.103" codeSystemName="ICD-9" /></value><entryRelationship typeCode="REFR"><observation classCode="OBS" moodCode="EVN"><templateId root="2.16.840.1.113883.10.20.1.50" /><templateId root="2.16.840.1.113883.3.249.11.100.12" /><id root="cbd74c57-71c3-460b-89cb-1401c2754745" /><code code="33999-4" codeSystem="2.16.840.1.113883.6.1" displayName="Status" /><statusCode code="active" /><value xsi:type="CE" code="55561003" codeSystem="2.16.840.1.113883.6.96" /></observation></entryRelationship></observation></entryRelationship></act></entry><entry><act classCode="ACT" moodCode="EVN"><templateId root="2.16.840.1.113883.3.88.11.83.7" /><templateId root="2.16.840.1.113883.10.20.1.27" /><templateId root="1.3.6.1.4.1.19376.1.5.3.1.4.5.1" /><templateId root="1.3.6.1.4.1.19376.1.5.3.1.4.5.2" /><id root="9c644a07-10e9-4230-aa6d-efae69e4db81" /><code nullFlavor="NA" /><statusCode code="active" /><effectiveTime><low value="20120301000000" /></effectiveTime><entryRelationship typeCode="SUBJ" inversionInd="false"><observation classCode="OBS" moodCode="EVN"><templateId root="2.16.840.1.113883.10.20.1.28" /><templateId root="1.3.6.1.4.1.19376.1.5.3.1.4.5" /><templateId root="2.16.840.1.113883.3.249.11.100.8" /><id root="a31b8411-cc35-4b60-9bca-8d66a24cf931" /><code code="55607006" codeSystem="2.16.840.1.113883.6.96" codeSystemName="SNOMED CT" displayName="Problem" /><text><reference value="#problem-ZZZZZ0031L" /></text><statusCode code="completed" /><effectiveTime><low value="20120301000000" /></effectiveTime><value xsi:type="CD" nullFlavor="UNK"><translation code="346.00" codeSystem="2.16.840.1.113883.6.103" codeSystemName="ICD-9" /></value><entryRelationship typeCode="REFR"><observation classCode="OBS" moodCode="EVN"><templateId root="2.16.840.1.113883.10.20.1.50" /><templateId root="2.16.840.1.113883.3.249.11.100.12" /><id root="09db3aa0-8928-4b6e-ab05-303652b0902b" /><code code="33999-4" codeSystem="2.16.840.1.113883.6.1" displayName="Status" /><statusCode code="active" /><value xsi:type="CE" code="55561003" codeSystem="2.16.840.1.113883.6.96" /></observation></entryRelationship></observation></entryRelationship></act></entry><entry><act classCode="ACT" moodCode="EVN"><templateId root="2.16.840.1.113883.3.88.11.83.7" /><templateId root="2.16.840.1.113883.10.20.1.27" /><templateId root="1.3.6.1.4.1.19376.1.5.3.1.4.5.1" /><templateId root="1.3.6.1.4.1.19376.1.5.3.1.4.5.2" /><id root="4ea28313-a55c-4279-8807-982c1097d4db" /><code nullFlavor="NA" /><statusCode code="active" /><effectiveTime><low value="20120301000000" /></effectiveTime><entryRelationship typeCode="SUBJ" inversionInd="false"><observation classCode="OBS" moodCode="EVN"><templateId root="2.16.840.1.113883.10.20.1.28" /><templateId root="1.3.6.1.4.1.19376.1.5.3.1.4.5" /><templateId root="2.16.840.1.113883.3.249.11.100.8" /><id root="a097f78f-1469-456c-89fa-22b49f0ba814" /><code code="55607006" codeSystem="2.16.840.1.113883.6.96" codeSystemName="SNOMED CT" displayName="Problem" /><text><reference value="#problem-ZZZZZ003HI" /></text><statusCode code="completed" /><effectiveTime><low value="20120301000000" /></effectiveTime><value xsi:type="CD" nullFlavor="UNK"><translation code="314.01" codeSystem="2.16.840.1.113883.6.103" codeSystemName="ICD-9" /></value><entryRelationship typeCode="REFR"><observation classCode="OBS" moodCode="EVN"><templateId root="2.16.840.1.113883.10.20.1.50" /><templateId root="2.16.840.1.113883.3.249.11.100.12" /><id root="036604c3-4f1c-4f0e-b7d0-b76d3b103d1e" /><code code="33999-4" codeSystem="2.16.840.1.113883.6.1" displayName="Status" /><statusCode code="active" /><value xsi:type="CE" code="55561003" codeSystem="2.16.840.1.113883.6.96" /></observation></entryRelationship></observation></entryRelationship></act></entry><entry><act classCode="ACT" moodCode="EVN"><templateId root="2.16.840.1.113883.3.88.11.83.7" /><templateId root="2.16.840.1.113883.10.20.1.27" /><templateId root="1.3.6.1.4.1.19376.1.5.3.1.4.5.1" /><templateId root="1.3.6.1.4.1.19376.1.5.3.1.4.5.2" /><id root="d407899a-71e6-4119-85c0-b174de855f27" /><code nullFlavor="NA" /><statusCode code="active" /><effectiveTime><low value="20120214000000" /></effectiveTime><entryRelationship typeCode="SUBJ" inversionInd="false"><observation classCode="OBS" moodCode="EVN"><templateId root="2.16.840.1.113883.10.20.1.28" /><templateId root="1.3.6.1.4.1.19376.1.5.3.1.4.5" /><templateId root="2.16.840.1.113883.3.249.11.100.8" /><id root="4d81d0d7-4440-4f33-8b37-6f001fabf517" /><code code="55607006" codeSystem="2.16.840.1.113883.6.96" codeSystemName="SNOMED CT" displayName="Problem" /><text><reference value="#problem-ZZZZZ000S2" /></text><statusCode code="completed" /><effectiveTime><low value="20120214000000" /></effectiveTime><value xsi:type="CD" nullFlavor="UNK"><translation code="346.10" codeSystem="2.16.840.1.113883.6.103" codeSystemName="ICD-9" /></value><entryRelationship typeCode="REFR"><observation classCode="OBS" moodCode="EVN"><templateId root="2.16.840.1.113883.10.20.1.50" /><templateId root="2.16.840.1.113883.3.249.11.100.12" /><id root="68641d19-862f-4c7a-99c5-ca64ce7169e3" /><code code="33999-4" codeSystem="2.16.840.1.113883.6.1" displayName="Status" /><statusCode code="active" /><value xsi:type="CE" code="55561003" codeSystem="2.16.840.1.113883.6.96" /></observation></entryRelationship></observation></entryRelationship></act></entry><entry><act classCode="ACT" moodCode="EVN"><templateId root="2.16.840.1.113883.3.88.11.83.7" /><templateId root="2.16.840.1.113883.10.20.1.27" /><templateId root="1.3.6.1.4.1.19376.1.5.3.1.4.5.1" /><templateId root="1.3.6.1.4.1.19376.1.5.3.1.4.5.2" /><id root="13af097b-689a-472f-a80f-eb36b0c91fca" /><code nullFlavor="NA" /><statusCode code="active" /><effectiveTime><low value="20120210000000" /></effectiveTime><entryRelationship typeCode="SUBJ" inversionInd="false"><observation classCode="OBS" moodCode="EVN"><templateId root="2.16.840.1.113883.10.20.1.28" /><templateId root="1.3.6.1.4.1.19376.1.5.3.1.4.5" /><templateId root="2.16.840.1.113883.3.249.11.100.8" /><id root="bbf0891f-82e7-407c-9726-1050d50ff771" /><code code="55607006" codeSystem="2.16.840.1.113883.6.96" codeSystemName="SNOMED CT" displayName="Problem" /><text><reference value="#problem-ZZZZZ001OP" /></text><statusCode code="completed" /><effectiveTime><low value="20120210000000" /></effectiveTime><value xsi:type="CD" nullFlavor="UNK"><translation code="346.00" codeSystem="2.16.840.1.113883.6.103" codeSystemName="ICD-9" /></value><entryRelationship typeCode="REFR"><observation classCode="OBS" moodCode="EVN"><templateId root="2.16.840.1.113883.10.20.1.50" /><templateId root="2.16.840.1.113883.3.249.11.100.12" /><id root="4e1d9c3c-ef31-4bb8-9c9a-b6807e05e6ae" /><code code="33999-4" codeSystem="2.16.840.1.113883.6.1" displayName="Status" /><statusCode code="active" /><value xsi:type="CE" code="55561003" codeSystem="2.16.840.1.113883.6.96" /></observation></entryRelationship></observation></entryRelationship></act></entry><entry><act classCode="ACT" moodCode="EVN"><templateId root="2.16.840.1.113883.3.88.11.83.7" /><templateId root="2.16.840.1.113883.10.20.1.27" /><templateId root="1.3.6.1.4.1.19376.1.5.3.1.4.5.1" /><templateId root="1.3.6.1.4.1.19376.1.5.3.1.4.5.2" /><id root="017d49fc-a964-4f10-829f-fe72a386e2f9" /><code nullFlavor="NA" /><statusCode code="active" /><effectiveTime><low value="20120208000000" /></effectiveTime><entryRelationship typeCode="SUBJ" inversionInd="false"><observation classCode="OBS" moodCode="EVN"><templateId root="2.16.840.1.113883.10.20.1.28" /><templateId root="1.3.6.1.4.1.19376.1.5.3.1.4.5" /><templateId root="2.16.840.1.113883.3.249.11.100.8" /><id root="33788955-2ac5-40de-99ae-c7d02f37d486" /><code code="55607006" codeSystem="2.16.840.1.113883.6.96" codeSystemName="SNOMED CT" displayName="Problem" /><text><reference value="#problem-ZZZZZ000DQ" /></text><statusCode code="completed" /><effectiveTime><low value="20120208000000" /></effectiveTime><value xsi:type="CD" nullFlavor="UNK"><translation code="780.99" codeSystem="2.16.840.1.113883.6.103" codeSystemName="ICD-9" /></value><entryRelationship typeCode="REFR"><observation classCode="OBS" moodCode="EVN"><templateId root="2.16.840.1.113883.10.20.1.50" /><templateId root="2.16.840.1.113883.3.249.11.100.12" /><id root="61edb9b4-5711-4566-a652-1e1d1d652285" /><code code="33999-4" codeSystem="2.16.840.1.113883.6.1" displayName="Status" /><statusCode code="active" /><value xsi:type="CE" code="55561003" codeSystem="2.16.840.1.113883.6.96" /></observation></entryRelationship></observation></entryRelationship></act></entry></section></component><component><section><templateId root="2.16.840.1.113883.3.88.11.83.112" assigningAuthorityName="HITSP/C83" /><templateId root="1.3.6.1.4.1.19376.1.5.3.1.3.19" assigningAuthorityName="IHE PCC" /><templateId root="2.16.840.1.113883.10.20.1.8" assigningAuthorityName="HL7 CCD" /><id root="75ab8839-673a-4b33-a0c8-1903a4952d6c" /><code code="10160-0" codeSystem="2.16.840.1.113883.6.1" codeSystemName="LOINC" displayName="Medications" /><title>Medication List</title><text><list><item><content styleCode="Bold">Flonase (<content ID="med-genericname-ZZZZZ005AC">Fluticasone Propionate</content>)</content>, 50mcg/1actuation Nasal Spray<br></br>2 spray(s) in each nostril daily<br></br>Last filled date 5/30/2012 by Kathie Teta</item><item><content styleCode="Bold"><content ID="med-genericname-ZZZZZ000N8">Phenobarbital</content></content>, 20mg/5ml Elixir<br></br>5 ml po bid.<br></br>Last filled date 2/20/2012 by Kathie Teta</item></list></text><entry typeCode="DRIV"><substanceAdministration classCode="SBADM" moodCode="INT"><templateId root="2.16.840.1.113883.3.88.11.83.8" assigningAuthorityName="HITSP/C83" /><templateId root="2.16.840.1.113883.10.20.1.24" assigningAuthorityName="CCD" /><templateId root="1.3.6.1.4.1.19376.1.5.3.1.4.7" assigningAuthorityName="IHE PCC" /><templateId root="1.3.6.1.4.1.19376.1.5.3.1.4.7.1" assigningAuthorityName="IHE PCC" /><id root="bef60961-3c67-45eb-a616-93cdb8029fc7" /><text>2 spray(s) in each nostril daily</text><statusCode code="completed" /><consumable><manufacturedProduct><templateId root="1.3.6.1.4.1.19376.1.5.3.1.4.7.2" assigningAuthorityName="IHE PCC" /><templateId root="2.16.840.1.113883.3.88.11.83.8.2" assigningAuthorityName="HITSP C83" /><templateId root="2.16.840.1.113883.10.20.1.53" assigningAuthorityName="CCD" /><manufacturedMaterial><code code="896323" codeSystem="2.16.840.1.113883.6.88" codeSystemName="RxNorm"><originalText><reference value="#med-genericname-ZZZZZ005AC" /></originalText></code><name>Flonase</name></manufacturedMaterial></manufacturedProduct></consumable><performer><assignedEntity><id root="2d46d531-7bca-498a-8673-b975a7b28cb0" /><addr use="WP"><streetAddressLine>5887 Glenridge Drive Suite 140</streetAddressLine><city>Atlanta</city><state>GA</state><postalCode>30326</postalCode><country /></addr><telecom use="WP" value="tel:(678)705-7341" /><telecom use="WP" value="fax:(678)973-0578" /><assignedPerson><name><given>Kathie</given><family>Teta</family></name></assignedPerson></assignedEntity></performer></substanceAdministration></entry><entry typeCode="DRIV"><substanceAdministration classCode="SBADM" moodCode="INT"><templateId root="2.16.840.1.113883.3.88.11.83.8" assigningAuthorityName="HITSP/C83" /><templateId root="2.16.840.1.113883.10.20.1.24" assigningAuthorityName="CCD" /><templateId root="1.3.6.1.4.1.19376.1.5.3.1.4.7" assigningAuthorityName="IHE PCC" /><templateId root="1.3.6.1.4.1.19376.1.5.3.1.4.7.1" assigningAuthorityName="IHE PCC" /><id root="84397375-2b9c-40fe-a860-8017d7bba18e" /><text>5 ml po bid.</text><statusCode code="completed" /><consumable><manufacturedProduct><templateId root="1.3.6.1.4.1.19376.1.5.3.1.4.7.2" assigningAuthorityName="IHE PCC" /><templateId root="2.16.840.1.113883.3.88.11.83.8.2" assigningAuthorityName="HITSP C83" /><templateId root="2.16.840.1.113883.10.20.1.53" assigningAuthorityName="CCD" /><manufacturedMaterial><code code="702519" codeSystem="2.16.840.1.113883.6.88" codeSystemName="RxNorm"><originalText><reference value="#med-genericname-ZZZZZ000N8" /></originalText></code><name>Phenobarbital</name></manufacturedMaterial></manufacturedProduct></consumable><performer><assignedEntity><id root="55c2f374-5466-4929-b270-f1f813db9afb" /><addr use="WP"><streetAddressLine>5887 Glenridge Drive Suite 140</streetAddressLine><city>Atlanta</city><state>GA</state><postalCode>30326</postalCode><country /></addr><telecom use="WP" value="tel:(678)705-7341" /><telecom use="WP" value="fax:(678)973-0578" /><assignedPerson><name><given>Kathie</given><family>Teta</family></name></assignedPerson></assignedEntity></performer></substanceAdministration></entry></section></component><component><section><templateId root="2.16.840.1.113883.10.20.1.2" /><templateId root="1.3.6.1.4.1.19376.1.5.3.1.3.13" /><templateId root="2.16.840.1.113883.3.88.11.83.102" /><id root="aca1fa7f-e505-470a-860d-4ea097a05d19" /><code code="48765-2" codeSystem="2.16.840.1.113883.6.1" codeSystemName="ALLERGIES AND ADVERSE REACTIONS" displayName="LOINC" /><title>Allergies and Adverse Reactions</title><text><list><item><content ID="allergy-cause-ZZZZZ00002">Phenytoin Sodium</content>: rash</item></list></text><entry typeCode="DRIV"><act classCode="ACT" moodCode="EVN"><templateId root="2.16.840.1.113883.10.20.1.27" /><templateId root="2.16.840.1.113883.3.88.11.83.6" /><templateId root="1.3.6.1.4.1.19376.1.5.3.1.4.5.1" /><templateId root="1.3.6.1.4.1.19376.1.5.3.1.4.5.3" /><id root="454decb6-db2b-4f84-a82e-79fcf6a57abb" /><code nullFlavor="NA" /><statusCode code="active" /><effectiveTime><low nullFlavor="UNK" /></effectiveTime><entryRelationship typeCode="SUBJ" inversionInd="false"><observation classCode="OBS" moodCode="EVN"><templateId root="2.16.840.1.113883.10.20.1.18" /><templateId root="1.3.6.1.4.1.19376.1.5.3.1.4.6" /><templateId root="1.3.6.1.4.1.19376.1.5.3.1.4.5" /><templateId root="2.16.840.1.113883.10.20.1.28" /><id root="30071e2e-3378-42c7-807f-de2191d35b84" /><code code="416098002" codeSystem="2.16.840.1.113883.6.96" codeSystemName="SNOMED CT" displayName="Drug allergy" /><text><reference value="#allergy-cause-ZZZZZ00002" /></text><statusCode code="completed" /><effectiveTime><low nullFlavor="UNK" /></effectiveTime><value xsi:type="CD" /><participant typeCode="CSM"><participantRole classCode="MANU"><playingEntity classCode="MMAT"><code><originalText><reference value="#allergy-cause-ZZZZZ00002" /></originalText></code><name>Phenytoin Sodium</name></playingEntity></participantRole></participant><entryRelationship typeCode="MFST"><observation classCode="OBS" moodCode="EVN"><templateId root="2.16.840.1.113883.10.20.1.54" /><code nullFlavor="NA" /><text>rash</text><statusCode code="completed" /></observation></entryRelationship><entryRelationship typeCode="SUBJ"><observation classCode="OBS" moodCode="EVN"><templateId root="2.16.840.1.113883.10.20.1.55" /><code code="SEV" codeSystem="2.16.840.1.113883.5.4" displayName="Severity observation" /><text>Moderate</text><statusCode code="completed" /><value xsi:type="CD" code="6736007" codeSystem="2.16.840.1.113883.3.88.12.3221.6.8" codeSystemName="SNOMED CT" displayName="Moderate" /></observation></entryRelationship></observation></entryRelationship></act></entry></section></component><component><section><templateId root="2.16.840.1.113883.10.20.1.10" /><templateId root="1.3.6.1.4.1.19376.1.5.3.1.3.31" /><id root="23b59899-4614-43d8-9e73-cc4283464e77" /><code code="18776-5" codeSystem="2.16.840.1.113883.6.1" codeSystemName="TREATMENT PLAN" displayName="LOINC" /><title>Plan Of Care</title><text><br></br><content styleCode="Bold Underline">Plan Section</content><br></br><content>No notes.</content><br></br><br></br><content styleCode="Bold Underline">Patient Recommendations</content><br></br><content>For  Complex Partial seizure w/o intract: </content><br></br><content></content><br></br><content></content><br></br></text></section></component></structuredBody></component></ClinicalDocument>